pygrenton/__init__.py
pygrenton/cipher.py
pygrenton/clu_client.py
pygrenton/config_objects.py
pygrenton/exceptions.py
pygrenton/gfeature.py
pygrenton/gmethod.py
pygrenton/gobject.py
pygrenton/interface_manager.py
pygrenton/interfaces.py
pygrenton/objects_classes.py
pygrenton/types.py
pygrenton/utils.py
pygrenton/parsers/config_json_parser.py
pygrenton/parsers/config_parser.py
pygrenton/parsers/interfaces_parser.py
pygrenton/parsers/om_parser.py
pygrenton-1.0.6.dist-info/METADATA
pygrenton-1.0.6.dist-info/WHEEL
pygrenton-1.0.6.dist-info/licenses/LICENSE
pygrenton-1.0.6.dist-info/RECORD
