Metadata-Version: 2.4
Name: pygrenton
Version: 1.0.6
Summary: Lightweight Python library to interact with grenton smart-home system.
Author-email: Paweł Rogaliński <progalin55@gmial.com>
License: MIT License
License-File: LICENSE
Classifier: License :: OSI Approved :: MIT License
Classifier: Operating System :: OS Independent
Classifier: Programming Language :: Python :: 3
Requires-Python: >=3.7
Requires-Dist: cryptography
